flask_barrier-1.0.0.dist-info/licenses/LICENSE
flask_guard/__init__.py
flask_guard/config.py
flask_guard/middleware.py
flask_guard/rules.py
flask_guard/utils.py
flask_barrier-1.0.0.dist-info/METADATA
flask_barrier-1.0.0.dist-info/WHEEL
flask_barrier-1.0.0.dist-info/top_level.txt
flask_barrier-1.0.0.dist-info/RECORD
